fastq_files/__init__.py
fastq_files-0.0.2.dist-info/LICENSE
fastq_files-0.0.2.dist-info/WHEEL
fastq_files-0.0.2.dist-info/METADATA
fastq_files-0.0.2.dist-info/RECORD
